{
  "meta": {
    "type": "person",
    "id": "collins-hawa-andrews",
    "name": "Collins, Hawa Andrews",
    "count": 31
  },
  "timeline": [
    {
      "year": 1988,
      "count": 2
    },
    {
      "year": 1990,
      "count": 2
    }
  ],
  "stackedTimeline": [
    {
      "year": 1988,
      "total": 2,
      "byType": {
        "Moving image": 2
      }
    },
    {
      "year": 1990,
      "total": 2,
      "byType": {
        "Moving image": 2
      }
    }
  ],
  "types": [
    {
      "name": "Moving image",
      "value": 31
    }
  ],
  "languages": [
    {
      "name": "English",
      "value": 31
    },
    {
      "name": "French",
      "value": 1
    }
  ],
  "subjects": [
    {
      "name": "Education",
      "value": 23
    },
    {
      "name": "Children",
      "value": 23
    },
    {
      "name": "Agriculture",
      "value": 3
    },
    {
      "name": "Music",
      "value": 3
    },
    {
      "name": "Culture",
      "value": 1
    },
    {
      "name": "History",
      "value": 1
    },
    {
      "name": "Singing",
      "value": 1
    },
    {
      "name": "Dance",
      "value": 1
    },
    {
      "name": "Card games",
      "value": 1
    },
    {
      "name": "Travel",
      "value": 1
    },
    {
      "name": "Music videos",
      "value": 1
    },
    {
      "name": "Food",
      "value": 1
    },
    {
      "name": "Crops",
      "value": 1
    },
    {
      "name": "Poets",
      "value": 1
    },
    {
      "name": "Novelists",
      "value": 1
    },
    {
      "name": "Interviews",
      "value": 1
    },
    {
      "name": "Concerts",
      "value": 1
    },
    {
      "name": "Christmas",
      "value": 1
    }
  ],
  "wordCloud": [
    {
      "name": "Education",
      "value": 23
    },
    {
      "name": "Children",
      "value": 23
    },
    {
      "name": "Educational Show",
      "value": 23
    },
    {
      "name": "Agriculture",
      "value": 3
    },
    {
      "name": "Music",
      "value": 3
    },
    {
      "name": "Live Music",
      "value": 3
    },
    {
      "name": "Consumer Advice",
      "value": 1
    },
    {
      "name": "Culture",
      "value": 1
    },
    {
      "name": "History",
      "value": 1
    },
    {
      "name": "Tradition",
      "value": 1
    },
    {
      "name": "Singing",
      "value": 1
    },
    {
      "name": "Dance",
      "value": 1
    },
    {
      "name": "Card games",
      "value": 1
    },
    {
      "name": "Travel",
      "value": 1
    },
    {
      "name": "Soap Opera",
      "value": 1
    },
    {
      "name": "Music videos",
      "value": 1
    },
    {
      "name": "Contemporary Music",
      "value": 1
    },
    {
      "name": "Food",
      "value": 1
    },
    {
      "name": "Crops",
      "value": 1
    },
    {
      "name": "Farming",
      "value": 1
    },
    {
      "name": "Poets",
      "value": 1
    },
    {
      "name": "Novelists",
      "value": 1
    },
    {
      "name": "Interviews",
      "value": 1
    },
    {
      "name": "Concerts",
      "value": 1
    },
    {
      "name": "Talk Show",
      "value": 1
    },
    {
      "name": "Christmas",
      "value": 1
    },
    {
      "name": "Public Affairs",
      "value": 1
    }
  ],
  "roles": [],
  "contributors": [
    {
      "name": "Government of Liberia",
      "value": 31
    },
    {
      "name": "Liberia Broadcasting System (LBS)",
      "value": 21
    },
    {
      "name": "Gilbert, Thomas",
      "value": 13
    },
    {
      "name": "Mensah, Sam",
      "value": 13
    },
    {
      "name": "Taylor, Adolphus",
      "value": 12
    },
    {
      "name": "Urey, Khrushchev Borbor",
      "value": 11
    },
    {
      "name": "McCrumada, Charles",
      "value": 11
    },
    {
      "name": "Wegee, Presley",
      "value": 10
    },
    {
      "name": "Flomo, Korkulor",
      "value": 8
    },
    {
      "name": "Eastman, John",
      "value": 8
    },
    {
      "name": "Fakay, Soko",
      "value": 7
    },
    {
      "name": "Kezele, Sumoiwuo",
      "value": 6
    },
    {
      "name": "Zeon, Jefferson",
      "value": 5
    },
    {
      "name": "Brent, Julius",
      "value": 5
    },
    {
      "name": "Caranda, Doughba C., II",
      "value": 4
    },
    {
      "name": "Forh, Juah",
      "value": 2
    },
    {
      "name": "Toby, Victor",
      "value": 2
    },
    {
      "name": "Ledlum, Leon Q.",
      "value": 1
    },
    {
      "name": "Frank, Bill",
      "value": 1
    },
    {
      "name": "Club 84: Musical Youth Byepopoleboe",
      "value": 1
    }
  ],
  "locations": [
    {
      "country": "Liberia",
      "region": "Montserrado County",
      "city": "Monrovia",
      "count": 31
    }
  ],
  "items": [
    {
      "_id": "6982337057a8e0353b0b1c42",
      "titleInfo": [
        {
          "title": "Food From the Soil"
        }
      ],
      "typeOfResource": "Moving image",
      "project": {
        "id": "UBT_ELTVTapes2021",
        "name": "U-Matic Tapes of the Liberia Broadcasting System"
      },
      "dre_id": "abn-99-0005"
    },
    {
      "_id": "6982337057a8e0353b0b1c43",
      "titleInfo": [
        {
          "title": "Food From the Soil"
        }
      ],
      "typeOfResource": "Moving image",
      "project": {
        "id": "UBT_ELTVTapes2021",
        "name": "U-Matic Tapes of the Liberia Broadcasting System"
      },
      "dre_id": "abn-99-0006"
    },
    {
      "_id": "6982337057a8e0353b0b1c7e",
      "titleInfo": [
        {
          "title": "Play School with Big Sister Hawa"
        }
      ],
      "typeOfResource": "Moving image",
      "project": {
        "id": "UBT_ELTVTapes2021",
        "name": "U-Matic Tapes of the Liberia Broadcasting System"
      },
      "dre_id": "abn-99-0041"
    },
    {
      "_id": "6982337057a8e0353b0b1c91",
      "titleInfo": [
        {
          "title": "Heritage Productions"
        }
      ],
      "typeOfResource": "Moving image",
      "project": {
        "id": "UBT_ELTVTapes2021",
        "name": "U-Matic Tapes of the Liberia Broadcasting System"
      },
      "dre_id": "abn-99-0054"
    },
    {
      "_id": "6982337057a8e0353b0b1c92",
      "titleInfo": [
        {
          "title": "Play School with Big Sister Hawa"
        }
      ],
      "typeOfResource": "Moving image",
      "project": {
        "id": "UBT_ELTVTapes2021",
        "name": "U-Matic Tapes of the Liberia Broadcasting System"
      },
      "dre_id": "abn-99-0055"
    },
    {
      "_id": "6982337057a8e0353b0b1c93",
      "titleInfo": [
        {
          "title": "Play School with Big Sister Hawa"
        }
      ],
      "typeOfResource": "Moving image",
      "project": {
        "id": "UBT_ELTVTapes2021",
        "name": "U-Matic Tapes of the Liberia Broadcasting System"
      },
      "dre_id": "abn-99-0056"
    },
    {
      "_id": "6982337057a8e0353b0b1c94",
      "titleInfo": [
        {
          "title": "Play School with Big Sister Hawa"
        }
      ],
      "typeOfResource": "Moving image",
      "project": {
        "id": "UBT_ELTVTapes2021",
        "name": "U-Matic Tapes of the Liberia Broadcasting System"
      },
      "dre_id": "abn-99-0057"
    },
    {
      "_id": "6982337057a8e0353b0b1c95",
      "titleInfo": [
        {
          "title": "Play School with Big Sister Hawa"
        }
      ],
      "typeOfResource": "Moving image",
      "project": {
        "id": "UBT_ELTVTapes2021",
        "name": "U-Matic Tapes of the Liberia Broadcasting System"
      },
      "dre_id": "abn-99-0058"
    },
    {
      "_id": "6982337057a8e0353b0b1c96",
      "titleInfo": [
        {
          "title": "Play School with Big Sister Hawa"
        }
      ],
      "typeOfResource": "Moving image",
      "project": {
        "id": "UBT_ELTVTapes2021",
        "name": "U-Matic Tapes of the Liberia Broadcasting System"
      },
      "dre_id": "abn-99-0059"
    },
    {
      "_id": "6982337057a8e0353b0b1c97",
      "titleInfo": [
        {
          "title": "Play School with Big Sister Hawa"
        }
      ],
      "typeOfResource": "Moving image",
      "project": {
        "id": "UBT_ELTVTapes2021",
        "name": "U-Matic Tapes of the Liberia Broadcasting System"
      },
      "dre_id": "abn-99-005a"
    },
    {
      "_id": "6982337057a8e0353b0b1c98",
      "titleInfo": [
        {
          "title": "Play School with Big Sister Hawa"
        }
      ],
      "typeOfResource": "Moving image",
      "project": {
        "id": "UBT_ELTVTapes2021",
        "name": "U-Matic Tapes of the Liberia Broadcasting System"
      },
      "dre_id": "abn-99-005b"
    },
    {
      "_id": "6982337057a8e0353b0b1c9a",
      "titleInfo": [
        {
          "title": "Play School with Big Sister Hawa"
        }
      ],
      "typeOfResource": "Moving image",
      "project": {
        "id": "UBT_ELTVTapes2021",
        "name": "U-Matic Tapes of the Liberia Broadcasting System"
      },
      "dre_id": "abn-99-005d"
    },
    {
      "_id": "6982337057a8e0353b0b1c9b",
      "titleInfo": [
        {
          "title": "Play School with Big Sister Hawa"
        }
      ],
      "typeOfResource": "Moving image",
      "project": {
        "id": "UBT_ELTVTapes2021",
        "name": "U-Matic Tapes of the Liberia Broadcasting System"
      },
      "dre_id": "abn-99-005e"
    },
    {
      "_id": "6982337057a8e0353b0b1c9c",
      "titleInfo": [
        {
          "title": "Play School with Big Sister Hawa"
        }
      ],
      "typeOfResource": "Moving image",
      "project": {
        "id": "UBT_ELTVTapes2021",
        "name": "U-Matic Tapes of the Liberia Broadcasting System"
      },
      "dre_id": "abn-99-005f"
    },
    {
      "_id": "6982337057a8e0353b0b1c9d",
      "titleInfo": [
        {
          "title": "Play School with Big Sister Hawa"
        }
      ],
      "typeOfResource": "Moving image",
      "project": {
        "id": "UBT_ELTVTapes2021",
        "name": "U-Matic Tapes of the Liberia Broadcasting System"
      },
      "dre_id": "abn-99-0060"
    },
    {
      "_id": "6982337057a8e0353b0b1ca6",
      "titleInfo": [
        {
          "title": "Play School with Big Sister Hawa"
        }
      ],
      "typeOfResource": "Moving image",
      "project": {
        "id": "UBT_ELTVTapes2021",
        "name": "U-Matic Tapes of the Liberia Broadcasting System"
      },
      "dre_id": "abn-99-0069"
    },
    {
      "_id": "6982337057a8e0353b0b1cab",
      "titleInfo": [
        {
          "title": "Spotlight"
        }
      ],
      "typeOfResource": "Moving image",
      "project": {
        "id": "UBT_ELTVTapes2021",
        "name": "U-Matic Tapes of the Liberia Broadcasting System"
      },
      "dre_id": "abn-99-006e"
    },
    {
      "_id": "6982337057a8e0353b0b1cad",
      "titleInfo": [
        {
          "title": "Heritage Productions  - Music Variety Show"
        }
      ],
      "typeOfResource": "Moving image",
      "project": {
        "id": "UBT_ELTVTapes2021",
        "name": "U-Matic Tapes of the Liberia Broadcasting System"
      },
      "dre_id": "abn-99-0070"
    },
    {
      "_id": "6982337057a8e0353b0b1cb0",
      "titleInfo": [
        {
          "title": "Food from the Soil"
        }
      ],
      "typeOfResource": "Moving image",
      "project": {
        "id": "UBT_ELTVTapes2021",
        "name": "U-Matic Tapes of the Liberia Broadcasting System"
      },
      "dre_id": "abn-99-0073"
    },
    {
      "_id": "6982337057a8e0353b0b1cd8",
      "titleInfo": [
        {
          "title": "Heritage Productions"
        }
      ],
      "typeOfResource": "Moving image",
      "project": {
        "id": "UBT_ELTVTapes2021",
        "name": "U-Matic Tapes of the Liberia Broadcasting System"
      },
      "dre_id": "abn-99-009b"
    },
    {
      "_id": "6982337057a8e0353b0b1d09",
      "titleInfo": [
        {
          "title": "Play School with Big Sister Hawa"
        }
      ],
      "typeOfResource": "Moving image",
      "project": {
        "id": "UBT_ELTVTapes2021",
        "name": "U-Matic Tapes of the Liberia Broadcasting System"
      },
      "dre_id": "abn-99-00cc"
    },
    {
      "_id": "6982337057a8e0353b0b1d0a",
      "titleInfo": [
        {
          "title": "Play School with Big Sister Hawa"
        }
      ],
      "typeOfResource": "Moving image",
      "project": {
        "id": "UBT_ELTVTapes2021",
        "name": "U-Matic Tapes of the Liberia Broadcasting System"
      },
      "dre_id": "abn-99-00cd"
    },
    {
      "_id": "6982337057a8e0353b0b1d1d",
      "titleInfo": [
        {
          "title": "Play School with Big Sister Hawa"
        }
      ],
      "typeOfResource": "Moving image",
      "project": {
        "id": "UBT_ELTVTapes2021",
        "name": "U-Matic Tapes of the Liberia Broadcasting System"
      },
      "dre_id": "abn-99-00e0"
    },
    {
      "_id": "6982337057a8e0353b0b1d1e",
      "titleInfo": [
        {
          "title": "Play School with Big Sister Hawa"
        }
      ],
      "typeOfResource": "Moving image",
      "project": {
        "id": "UBT_ELTVTapes2021",
        "name": "U-Matic Tapes of the Liberia Broadcasting System"
      },
      "dre_id": "abn-99-00e1"
    },
    {
      "_id": "6982337057a8e0353b0b1d1f",
      "titleInfo": [
        {
          "title": "Play School with Big Sister Hawa"
        }
      ],
      "typeOfResource": "Moving image",
      "project": {
        "id": "UBT_ELTVTapes2021",
        "name": "U-Matic Tapes of the Liberia Broadcasting System"
      },
      "dre_id": "abn-99-00e2"
    },
    {
      "_id": "6982337057a8e0353b0b1d20",
      "titleInfo": [
        {
          "title": "Play School with Big Sister Hawa"
        }
      ],
      "typeOfResource": "Moving image",
      "project": {
        "id": "UBT_ELTVTapes2021",
        "name": "U-Matic Tapes of the Liberia Broadcasting System"
      },
      "dre_id": "abn-99-00e3"
    },
    {
      "_id": "6982337057a8e0353b0b1d29",
      "titleInfo": [
        {
          "title": "Play School with Big Sister Hawa"
        }
      ],
      "typeOfResource": "Moving image",
      "project": {
        "id": "UBT_ELTVTapes2021",
        "name": "U-Matic Tapes of the Liberia Broadcasting System"
      },
      "dre_id": "abn-99-00ec"
    },
    {
      "_id": "6982337057a8e0353b0b1d2a",
      "titleInfo": [
        {
          "title": "Play School with Big Sister Hawa"
        }
      ],
      "typeOfResource": "Moving image",
      "project": {
        "id": "UBT_ELTVTapes2021",
        "name": "U-Matic Tapes of the Liberia Broadcasting System"
      },
      "dre_id": "abn-99-00ed"
    },
    {
      "_id": "6982337057a8e0353b0b1d88",
      "titleInfo": [
        {
          "title": "Special Feature"
        }
      ],
      "typeOfResource": "Moving image",
      "project": {
        "id": "UBT_ELTVTapes2021",
        "name": "U-Matic Tapes of the Liberia Broadcasting System"
      },
      "dre_id": "abn-99-014b"
    },
    {
      "_id": "6982337057a8e0353b0b1daa",
      "titleInfo": [
        {
          "title": "Play School with Big Sister Hawa"
        }
      ],
      "typeOfResource": "Moving image",
      "project": {
        "id": "UBT_ELTVTapes2021",
        "name": "U-Matic Tapes of the Liberia Broadcasting System"
      },
      "dre_id": "abn-99-016d"
    },
    {
      "_id": "6982337057a8e0353b0b1dab",
      "titleInfo": [
        {
          "title": "Play School with Big Sister Hawa"
        }
      ],
      "typeOfResource": "Moving image",
      "project": {
        "id": "UBT_ELTVTapes2021",
        "name": "U-Matic Tapes of the Liberia Broadcasting System"
      },
      "dre_id": "abn-99-016e"
    }
  ]
}