{"nodes":[{"id":"item:abx-01-0045","name":"Ohne Titel","category":0,"symbolSize":35},{"id":"person:Collections@UBT","name":"Collections@UBT","category":1,"symbolSize":18},{"id":"person:Spittler, Gerd","name":"Spittler, Gerd","category":1,"symbolSize":18},{"id":"subject:Photography","name":"Photography","category":2,"symbolSize":14},{"id":"subject:Anthropology","name":"Anthropology","category":2,"symbolSize":14},{"id":"subject:Festivals","name":"Festivals","category":2,"symbolSize":14},{"id":"subject:Tuaregs","name":"Tuaregs","category":2,"symbolSize":14},{"id":"subject:Photographs","name":"Photographs","category":2,"symbolSize":14},{"id":"tag:Eröffnungsfeier","name":"Eröffnungsfeier","category":3,"symbolSize":12},{"id":"tag:Sammlung Gerd Spittler","name":"Sammlung Gerd Spittler","category":3,"symbolSize":12},{"id":"loc:Iférouane","name":"Iférouane","category":4,"symbolSize":16},{"id":"proj:The Pre-Death Bequest of Gerd Spittler","name":"The Pre-Death Bequest of Gerd Spittler","category":5,"symbolSize":20},{"id":"genre:picture","name":"picture","category":6,"symbolSize":14},{"id":"item:abx-01-0044","name":"Ohne Titel","category":0,"symbolSize":12},{"id":"item:abx-01-0021","name":"Ohne Titel","category":0,"symbolSize":12},{"id":"item:abx-01-0025","name":"Ohne Titel","category":0,"symbolSize":12},{"id":"item:abx-01-0023","name":"Ohne Titel","category":0,"symbolSize":12},{"id":"item:abx-01-0026","name":"Ohne Titel","category":0,"symbolSize":12},{"id":"item:abx-01-001f","name":"Ohne Titel","category":0,"symbolSize":12},{"id":"item:abx-01-002d","name":"Ohne Titel","category":0,"symbolSize":12},{"id":"item:abx-01-0019","name":"Ohne Titel","category":0,"symbolSize":12},{"id":"item:abx-01-0043","name":"Ohne Titel","category":0,"symbolSize":12}],"links":[{"source":"item:abx-01-0045","target":"person:Collections@UBT"},{"source":"item:abx-01-0045","target":"person:Spittler, Gerd"},{"source":"item:abx-01-0045","target":"subject:Photography"},{"source":"item:abx-01-0045","target":"subject:Anthropology"},{"source":"item:abx-01-0045","target":"subject:Festivals"},{"source":"item:abx-01-0045","target":"subject:Tuaregs"},{"source":"item:abx-01-0045","target":"subject:Photographs"},{"source":"item:abx-01-0045","target":"tag:Eröffnungsfeier"},{"source":"item:abx-01-0045","target":"tag:Sammlung Gerd Spittler"},{"source":"item:abx-01-0045","target":"loc:Iférouane"},{"source":"item:abx-01-0045","target":"proj:The Pre-Death Bequest of Gerd Spittler"},{"source":"item:abx-01-0045","target":"genre:picture"},{"source":"item:abx-01-0044","target":"person:Collections@UBT"},{"source":"item:abx-01-0044","target":"person:Spittler, Gerd"},{"source":"item:abx-01-0044","target":"subject:Photography"},{"source":"item:abx-01-0044","target":"subject:Anthropology"},{"source":"item:abx-01-0044","target":"subject:Festivals"},{"source":"item:abx-01-0044","target":"subject:Tuaregs"},{"source":"item:abx-01-0044","target":"subject:Photographs"},{"source":"item:abx-01-0044","target":"tag:Eröffnungsfeier"},{"source":"item:abx-01-0044","target":"tag:Sammlung Gerd Spittler"},{"source":"item:abx-01-0044","target":"loc:Iférouane"},{"source":"item:abx-01-0044","target":"proj:The Pre-Death Bequest of Gerd Spittler"},{"source":"item:abx-01-0044","target":"genre:picture"},{"source":"item:abx-01-0021","target":"person:Collections@UBT"},{"source":"item:abx-01-0021","target":"person:Spittler, Gerd"},{"source":"item:abx-01-0021","target":"subject:Photography"},{"source":"item:abx-01-0021","target":"subject:Anthropology"},{"source":"item:abx-01-0021","target":"subject:Festivals"},{"source":"item:abx-01-0021","target":"subject:Tuaregs"},{"source":"item:abx-01-0021","target":"subject:Photographs"},{"source":"item:abx-01-0021","target":"tag:Sammlung Gerd Spittler"},{"source":"item:abx-01-0021","target":"loc:Iférouane"},{"source":"item:abx-01-0021","target":"proj:The Pre-Death Bequest of Gerd Spittler"},{"source":"item:abx-01-0021","target":"genre:picture"},{"source":"item:abx-01-0025","target":"person:Collections@UBT"},{"source":"item:abx-01-0025","target":"person:Spittler, Gerd"},{"source":"item:abx-01-0025","target":"subject:Photography"},{"source":"item:abx-01-0025","target":"subject:Anthropology"},{"source":"item:abx-01-0025","target":"subject:Festivals"},{"source":"item:abx-01-0025","target":"subject:Tuaregs"},{"source":"item:abx-01-0025","target":"subject:Photographs"},{"source":"item:abx-01-0025","target":"tag:Sammlung Gerd Spittler"},{"source":"item:abx-01-0025","target":"loc:Iférouane"},{"source":"item:abx-01-0025","target":"proj:The Pre-Death Bequest of Gerd Spittler"},{"source":"item:abx-01-0025","target":"genre:picture"},{"source":"item:abx-01-0023","target":"person:Collections@UBT"},{"source":"item:abx-01-0023","target":"person:Spittler, Gerd"},{"source":"item:abx-01-0023","target":"subject:Photography"},{"source":"item:abx-01-0023","target":"subject:Anthropology"},{"source":"item:abx-01-0023","target":"subject:Festivals"},{"source":"item:abx-01-0023","target":"subject:Photographs"},{"source":"item:abx-01-0023","target":"tag:Sammlung Gerd Spittler"},{"source":"item:abx-01-0023","target":"loc:Iférouane"},{"source":"item:abx-01-0023","target":"proj:The Pre-Death Bequest of Gerd Spittler"},{"source":"item:abx-01-0023","target":"genre:picture"},{"source":"item:abx-01-0026","target":"person:Collections@UBT"},{"source":"item:abx-01-0026","target":"person:Spittler, Gerd"},{"source":"item:abx-01-0026","target":"subject:Photography"},{"source":"item:abx-01-0026","target":"subject:Anthropology"},{"source":"item:abx-01-0026","target":"subject:Festivals"},{"source":"item:abx-01-0026","target":"subject:Photographs"},{"source":"item:abx-01-0026","target":"tag:Sammlung Gerd Spittler"},{"source":"item:abx-01-0026","target":"loc:Iférouane"},{"source":"item:abx-01-0026","target":"proj:The Pre-Death Bequest of Gerd Spittler"},{"source":"item:abx-01-0026","target":"genre:picture"},{"source":"item:abx-01-001f","target":"person:Collections@UBT"},{"source":"item:abx-01-001f","target":"person:Spittler, Gerd"},{"source":"item:abx-01-001f","target":"subject:Photography"},{"source":"item:abx-01-001f","target":"subject:Anthropology"},{"source":"item:abx-01-001f","target":"subject:Festivals"},{"source":"item:abx-01-001f","target":"subject:Photographs"},{"source":"item:abx-01-001f","target":"tag:Sammlung Gerd Spittler"},{"source":"item:abx-01-001f","target":"loc:Iférouane"},{"source":"item:abx-01-001f","target":"proj:The Pre-Death Bequest of Gerd Spittler"},{"source":"item:abx-01-001f","target":"genre:picture"},{"source":"item:abx-01-002d","target":"subject:Tuaregs"},{"source":"item:abx-01-0019","target":"subject:Tuaregs"},{"source":"item:abx-01-0043","target":"subject:Tuaregs"}],"categories":[{"name":"Research Item"},{"name":"Person"},{"name":"Subject"},{"name":"Tag"},{"name":"Location"},{"name":"Project"},{"name":"Genre"},{"name":"Institution"}]}