{"nodes":[{"id":"item:eaa-99-0045","name":"Music in African churches","category":0,"symbolSize":35},{"id":"person:Lury, Canon E. E.","name":"Lury, Canon E. E.","category":1,"symbolSize":18},{"id":"subject:Ethnomusicology","name":"Ethnomusicology","category":2,"symbolSize":14},{"id":"subject:Church music","name":"Church music","category":2,"symbolSize":14},{"id":"subject:Gregorian chants","name":"Gregorian chants","category":2,"symbolSize":14},{"id":"subject:Pentatonic scales","name":"Pentatonic scales","category":2,"symbolSize":14},{"id":"subject:Africa","name":"Africa","category":2,"symbolSize":14},{"id":"subject:Musical ability","name":"Musical ability","category":2,"symbolSize":14},{"id":"tag:African Music","name":"African Music","category":3,"symbolSize":12},{"id":"loc:South Africa","name":"South Africa","category":4,"symbolSize":16},{"id":"item:eaa-99-003e","name":"Notes on Canon Lury's article","category":0,"symbolSize":12},{"id":"item:eaa-99-010e","name":"Impressions of African Church music","category":0,"symbolSize":12},{"id":"item:eaa-99-009b","name":"Changing times","category":0,"symbolSize":12},{"id":"item:eaa-99-01ad","name":"The musical dimension of perception in the upper Congo, Zae","category":0,"symbolSize":12},{"id":"item:eaa-99-01c0","name":"Les membranophones des Luba-Shankadi","category":0,"symbolSize":12},{"id":"item:eaa-99-00cd","name":"A case for the name Mbira","category":0,"symbolSize":12},{"id":"item:eaa-99-010f","name":"Music in Nigeria","category":0,"symbolSize":12}],"links":[{"source":"item:eaa-99-0045","target":"person:Lury, Canon E. E.","label":"contributor"},{"source":"item:eaa-99-0045","target":"subject:Ethnomusicology","label":"has subject"},{"source":"item:eaa-99-0045","target":"subject:Church music","label":"has subject"},{"source":"item:eaa-99-0045","target":"subject:Gregorian chants","label":"has subject"},{"source":"item:eaa-99-0045","target":"subject:Pentatonic scales","label":"has subject"},{"source":"item:eaa-99-0045","target":"subject:Africa","label":"has subject"},{"source":"item:eaa-99-0045","target":"subject:Musical ability","label":"has subject"},{"source":"item:eaa-99-0045","target":"tag:African Music","label":"tagged"},{"source":"item:eaa-99-0045","target":"loc:South Africa","label":"created at"},{"source":"item:eaa-99-0045","target":"item:eaa-99-003e","label":"shares subject: Ethnomusicology, subject: Church music, subject: Gregorian chants, subject: Africa, tag: African Music, location: South Africa"},{"source":"item:eaa-99-003e","target":"subject:Ethnomusicology"},{"source":"item:eaa-99-003e","target":"subject:Church music"},{"source":"item:eaa-99-003e","target":"subject:Gregorian chants"},{"source":"item:eaa-99-003e","target":"subject:Africa"},{"source":"item:eaa-99-003e","target":"tag:African Music"},{"source":"item:eaa-99-003e","target":"loc:South Africa"},{"source":"item:eaa-99-0045","target":"item:eaa-99-010e","label":"shares subject: Ethnomusicology, subject: Church music, subject: Africa, tag: African Music, location: South Africa"},{"source":"item:eaa-99-010e","target":"subject:Ethnomusicology"},{"source":"item:eaa-99-010e","target":"subject:Church music"},{"source":"item:eaa-99-010e","target":"subject:Africa"},{"source":"item:eaa-99-010e","target":"tag:African Music"},{"source":"item:eaa-99-010e","target":"loc:South Africa"},{"source":"item:eaa-99-0045","target":"item:eaa-99-009b","label":"shares subject: Ethnomusicology, subject: Church music, subject: Africa, tag: African Music, location: South Africa"},{"source":"item:eaa-99-009b","target":"subject:Ethnomusicology"},{"source":"item:eaa-99-009b","target":"subject:Church music"},{"source":"item:eaa-99-009b","target":"subject:Africa"},{"source":"item:eaa-99-009b","target":"tag:African Music"},{"source":"item:eaa-99-009b","target":"loc:South Africa"},{"source":"item:eaa-99-0045","target":"item:eaa-99-01ad","label":"shares subject: Ethnomusicology, subject: Africa, tag: African Music, location: South Africa"},{"source":"item:eaa-99-01ad","target":"subject:Ethnomusicology"},{"source":"item:eaa-99-01ad","target":"subject:Africa"},{"source":"item:eaa-99-01ad","target":"tag:African Music"},{"source":"item:eaa-99-01ad","target":"loc:South Africa"},{"source":"item:eaa-99-0045","target":"item:eaa-99-01c0","label":"shares subject: Ethnomusicology, subject: Africa, tag: African Music, location: South Africa"},{"source":"item:eaa-99-01c0","target":"subject:Ethnomusicology"},{"source":"item:eaa-99-01c0","target":"subject:Africa"},{"source":"item:eaa-99-01c0","target":"tag:African Music"},{"source":"item:eaa-99-01c0","target":"loc:South Africa"},{"source":"item:eaa-99-0045","target":"item:eaa-99-00cd","label":"shares subject: Ethnomusicology, subject: Africa, tag: African Music, location: South Africa"},{"source":"item:eaa-99-00cd","target":"subject:Ethnomusicology"},{"source":"item:eaa-99-00cd","target":"subject:Africa"},{"source":"item:eaa-99-00cd","target":"tag:African Music"},{"source":"item:eaa-99-00cd","target":"loc:South Africa"},{"source":"item:eaa-99-0045","target":"item:eaa-99-010f","label":"shares subject: Church music"},{"source":"item:eaa-99-010f","target":"subject:Church music"}],"categories":[{"name":"Research Item"},{"name":"Person"},{"name":"Subject"},{"name":"Tag"},{"name":"Location"},{"name":"Project"},{"name":"Genre"},{"name":"Institution"}]}